numpydoc_tools/__init__.py
numpydoc_tools/main.py
numpydoc_tools-0.1.0.dist-info/entry_points.txt
numpydoc_tools-0.1.0.dist-info/LICENSE
numpydoc_tools-0.1.0.dist-info/WHEEL
numpydoc_tools-0.1.0.dist-info/METADATA
numpydoc_tools-0.1.0.dist-info/RECORD
